README.rst
setup.py
multisettings/__init__.py
multisettings.egg-info/PKG-INFO
multisettings.egg-info/SOURCES.txt
multisettings.egg-info/dependency_links.txt
multisettings.egg-info/entry_points.txt
multisettings.egg-info/top_level.txt