Metadata-Version: 1.1
Name: multisettings
Version: 1.0.0
Summary: Tool to handle multiple settings for editor, shell and other command line tools.
Home-page: http://github.com/wkentaro/multisettings
Author: Kentaro Wada
Author-email: www.kentaro.wada@gmail.com
License: MIT
Keywords: utility
Platform: UNKNOWN
Classifier: Development Status :: 5 - Production/Stable
Classifier: Intended Audience :: Developers
Classifier: License :: OSI Approved :: MIT License
Classifier: Operating System :: POSIX
Classifier: Topic :: Internet :: WWW/HTTP
